
[{
  "time": "9:00-10:30",
  "mon": "Matematika",
  "tue": "",
  "wed": "",
  "thu": "",
  "fri": ""
},
  {
    "time": "9:00-10:30",
    "mon": "Matematika",
    "tue": "",
    "wed": "",
    "thu": "",
    "fri": ""
  },
  {
    "time": "11:00-12:30",
    "mon": "Matematika",
    "tue": "",
    "wed": "",
    "thu": "",
    "fri": ""
  },
  {
    "time": "13:30-15:00",
    "mon": "Matematika",
    "tue": "",
    "wed": "",
    "thu": "",
    "fri": ""
  },
  {
    "time": "15:30-17:00",
    "mon": "Matematika",
    "tue": "",
    "wed": "",
    "thu": "",
    "fri": ""
  }
]